hermes_stream_nodes/__init__.py
hermes_stream_nodes/generic_stream.py
hermes_stream_nodes/serial_stream.py
hermes_stream_nodes/stream_counter.py
hermes_stream_nodes-1.0.3.dist-info/METADATA
hermes_stream_nodes-1.0.3.dist-info/WHEEL
hermes_stream_nodes-1.0.3.dist-info/RECORD
