Metadata-Version: 2.4
Name: hermes-stream-nodes
Version: 1.0.3
Summary: Hermes stream nodes
Author-email: floris vernieuwe <floris@vernieuwe.eu>
Requires-Python: >=3.10
Requires-Dist: node-hermes-core>=1.2.0
Requires-Dist: pyserial>=3.5
